{
  "persons": [
    {
      "name": "Mary Poppendieck",
      "number": "39-23-6423122",
      "id": 4
    },
    {
      "name": "Giorgio",
      "number": "3314148699",
      "id": 5
    },
    {
      "name": "Arto Hellas",
      "number": "040-123456",
      "id": 6
    },
    {
      "name": "giorgio",
      "number": "33333",
      "id": 7
    },
    {
      "name": "ciaooo",
      "number": "2",
      "id": 8
    },
    {
      "name": "cccc",
      "number": "",
      "id": 9
    },
    {
      "name": "ciao",
      "number": "come",
      "id": 10
    }
  ]
}